lxns-0.1.0.dist-info/METADATA
lxns-0.1.0.dist-info/WHEEL
lxns-0.1.0.dist-info/RECORD
lxns/os.abi3.so
lxns/__init__.py
lxns/os.py
lxns/namespaces.py
lxns/mount.py
lxns/py.typed
