Metadata-Version: 2.1
Name: lxns
Version: 0.1.0
Summary: Python library to interact with Linux kernel namespaces.
Keywords: linux namespace namespaces mount sandbox containers
Author: igo95862
License: MPL-2.0
Classifier: Development Status :: 4 - Beta
Classifier: Intended Audience :: Developers
Classifier: License :: OSI Approved :: Mozilla Public License 2.0 (MPL 2.0)
Classifier: Operating System :: POSIX :: Linux
Classifier: Programming Language :: Python :: 3
Classifier: Topic :: Security
Classifier: Topic :: Software Development :: Libraries
Classifier: Topic :: System :: Operating System Kernels :: Linux
Project-URL: Homepage, https://github.com/igo95862/python-lxns
Project-URL: Documentation, https://python-lxns.readthedocs.io/en/latest/
Project-URL: Repository, https://github.com/igo95862/python-lxns.git
Project-URL: Issues, https://github.com/igo95862/python-lxns/issues
Project-URL: Changelog, https://github.com/igo95862/python-lxns/blob/master/CHANGELOG.md
Requires-Python: >=3.7
